{
    "tables": [
        {
            "coordinate" : {
                "x": 10,
                "y": 10
            },
            "chairs": [
                {
                    "coordinate": {
                        "x": 15,
                        "y": 15
                    },
                    "occupied": false
                },
                {
                    "coordinate": {
                      "x": 15,
                      "y": 5
                    },
                    "occupied": true
                },
                {
                   "coordinate": {
                     "x": 10,
                     "y": 5
                   },
                   "occupied": false
                },
                {
                   "coordinate": {
                     "x": 10,
                     "y": 15
                   },
                   "occupied": false
                }
            ]
        },
        {
                   "coordinate" : {
                       "x": 30,
                       "y": 30
                   },
                   "chairs": [
                       {
                           "coordinate": {
                               "x": 35,
                               "y": 35
                           },
                           "occupied": false
                       },
                       {
                           "coordinate": {
                             "x": 35,
                             "y": 25
                           },
                           "occupied": true
                       },
                       {
                          "coordinate": {
                            "x": 30,
                            "y": 25
                          },
                          "occupied": false
                       },
                       {
                          "coordinate": {
                            "x": 30,
                            "y": 35
                          },
                          "occupied": false
                       }
                   ]
               }
    ]
}
